auto_browse/__init__.py
auto_browse/agents/action.py
auto_browse/browse/browse.py
auto_browse/dependencies/common_dependencies.py
auto_browse/prompts/action.py
auto_browse/telemetry/__init__.py
auto_browse/tools/browser_actions.py
auto_browse-0.0.5.dist-info/METADATA
auto_browse-0.0.5.dist-info/WHEEL
auto_browse-0.0.5.dist-info/licenses/LICENSE
auto_browse-0.0.5.dist-info/RECORD
