Metadata-Version: 2.4
Name: auto-browse
Version: 0.0.5
Summary: Test Automation using AI Agents
Author: Gurvinder Dhillon
License-File: LICENSE
Classifier: License :: OSI Approved :: MIT License
Classifier: Operating System :: OS Independent
Classifier: Programming Language :: Python :: 3
Requires-Python: >=3.11
Requires-Dist: browser-use>=0.1.27
Requires-Dist: lxml-html-clean>=0.4.1
Requires-Dist: maincontentextractor>=0.0.4
Requires-Dist: pip>=24.3.1
Requires-Dist: playwright>=1.49.1
Requires-Dist: pydantic-ai>=0.0.18
Requires-Dist: pydantic-graph>=0.0.19
Requires-Dist: python-dotenv>=1.0.1
Requires-Dist: tld==0.13
